shortcut_util/__init__.py
shortcut_util/const.py
shortcut_util/converter.py
shortcut_util/decorator.py
shortcut_util/email.py
shortcut_util/env.py
shortcut_util/ftp.py
shortcut_util/log.py
shortcut_util/singleton.py
shortcut_util/time.py
shortcut_util/unique.py
shortcut_util-0.0.5.dist-info/LICENSE
shortcut_util-0.0.5.dist-info/METADATA
shortcut_util-0.0.5.dist-info/WHEEL
shortcut_util-0.0.5.dist-info/top_level.txt
shortcut_util-0.0.5.dist-info/RECORD
